perceptible/__init__.py
perceptible/_version.py
perceptible/observable.py
perceptible/observableDictionary.py
perceptible/observableList.py
perceptible-0.4.2.dist-info/METADATA
perceptible-0.4.2.dist-info/RECORD
perceptible-0.4.2.dist-info/WHEEL
perceptible-0.4.2.dist-info/top_level.txt
