Metadata-Version: 2.1
Name: perceptible
Version: 0.4.2
Summary: Observable versions of python data structures
Home-page: https://github.com/chrisbrake/perceptible
Author: Chris Brake
Author-email: chris.brake@gmail.com
License: UNKNOWN
Keywords: perceptible,observable,observer
Platform: UNKNOWN
Classifier: License :: OSI Approved :: BSD License
Classifier: Programming Language :: Python
Classifier: Topic :: Software Development :: Libraries
